cr_sendmail/__init__.py
cr_sendmail/backends.py
cr_sendmail_django-1.0.dist-info/licenses/LICENSE.txt
django_sendmail_backend/__init__.py
django_sendmail_backend/backends.py
cr_sendmail_django-1.0.dist-info/METADATA
cr_sendmail_django-1.0.dist-info/WHEEL
cr_sendmail_django-1.0.dist-info/top_level.txt
cr_sendmail_django-1.0.dist-info/RECORD
