Metadata-Version: 2.4
Name: cr-sendmail-django
Version: 1.0
Summary: Django email backend which invokes system `sendmail` binary.
Author-email: CodeRed LLC <info@coderedcorp.com>
Project-URL: Source, https://github.com/coderedcorp/cr-sendmail-django
Classifier: Intended Audience :: Developers
Classifier: Natural Language :: English
Classifier: Operating System :: OS Independent
Classifier: Programming Language :: Python :: 3
Classifier: Programming Language :: Python :: 3 :: Only
Classifier: Framework :: Django
Requires-Python: >=3.6
License-File: LICENSE.txt
Requires-Dist: Django>=1.3
Dynamic: license-file
